Workbook

Sheet README
B2: Objetivos do projeto:
B3: Desenvolver competências práticas de Excel aplicado às finanças.
B4: Organizar e relacionar base de dados empresariais e financeiras.
B5: Clacular indicadores de desempenho financeiro.
B6: Analisar demonstrações financeiras e uma carteira de investimentos simulada.
B7: Construir Dashboard para facilitar a interpretação dos resultados.
B8: Demonstrar competências analíticas relevantes para oprotunidades nas áreas de Finançãs, Contabilidade e Dados.

Sheet tbEmpresas
B2: tbEmpresas
B3: ID_Empresa | C3: Nome_Empresa | D3: CNPJ | E3: Ticker | F3: Setor | G3: Segmento | H3: País | I3: Bolsa | J3: Tipo_Dado | K3: Fonte | L3: Data_Atualizacao
B4: EMP001 | C4: Petrobras | D4: 33.000.167/0001-01 | E4: PETR4 | F4: Petróleo e gás | G4: Energia | H4: Brasil | I4: B3 | J4: Real | K4: B3 | L4: 46293
B5: EMP002 | C5: Vale | D5: 33.592.510/0001-54 | E5: VALE3 | F5: Mineração | G5: Mineração | H5: Brasil | I5: B3 | J5: Real | K5: B3 | L5: 46293
B6: EMP003 | C6: Itaú Unibanco | D6: 60.872.504/0001-23 | E6: ITUB4 | F6: Financeiro | G6: Bancos | H6: Brasil | I6: B3 | J6: Real | K6: B3 | L6: 46293
B7: EMP004 | C7: Ambev | D7: 07.526.557/0001-00 | E7: ABEV3 | F7: Consumo | G7: Bebidas | H7: Brasil | I7: B3 | J7: Real | K7: B3 | L7: 46293
B8: EMP005 | C8: WEG | D8: 84.429.695/0001-11 | E8: WEGE3 | F8: Indústria | G8: Equipamentos elétricos | H8: Brasil | I8: B3 | J8: Real | K8: B3 | L8: 46293

Sheet tbAtivos
B2: tbAtivos
C3: Petrobras | D3: Vale | E3: Itaú Unibanco | F3: Ambev | G3: WEG
B4: ID_Ativo | C4: ATI001 | D4: ATI002 | E4: ATI003 | F4: ATI004 | G4: ATI005
B5: Ticker | C5: PETR4 | D5: VALE3 | E5: ITUB4 | F5: ABEV3 | G5: WEGE3
B6: Nome_Ativo | C6: Petrobras PN | D6: Vale ON | E6: Itaú Unibanco PN | F6: Ambev ON | G6: WEG ON
B7: ID_Empresa | C7: EMP001 | D7: EMP002 | E7: EMP003 | F7: EMP004 | G7: EMP005
B8: Classe_Ativo | C8: Ação | D8: Ação | E8: Ação | F8: Ação | G8: Ação
B9: Tipo_Ativo | C9: Renda Variável | D9: Renda variável | E9: Renda variável | F9: Renda variável | G9: Renda variável
B10: Mercado | C10: B3 | D10: B3 | E10: B3 | F10: B3 | G10: B3
B11: Moeda | C11: BRL | D11: BRL | E11: BRL | F11: BRL | G11: BRL
B12: Setor | C12: Petróleo e gás | D12: Mineração | E12: Financeiro | F12: Consumo | G12: Indústria
B13: Tipo_Dado | C13: Real | D13: Real | E13: Real | F13: Real | G13: Real

Sheet tbPrecosMercado
B2: tbPrecosMercado
C3: Petrobras - 01/09/2026 | D3: Petrobras - 02/09/2026 | E3: Petrobras - 03/09/2026 | F3: Itaú Unibanco - 01/09/2026 | G3: Itaú Unibanco - 02/09/2026 | H3: Itaú Unibanco - 03/09/2026 | I3: Vale - 01/09/2026 | J3: Vale - 02/09/2026 | K3: Vale - 03/09/2026 | L3: Ambev - 01/09/2026 | M3: Ambev - 02/09/2026 | N3: Ambev - 03/09/2026 | O3: Weg - 01/09/2026 | P3: Weg - 02/09/2026 | Q3: Weg - 03/09/2026
B4: ID_Preco | C4: PRE001 | D4: PRE002 | E4: PRE003 | F4: PRE007 | G4: PRE008 | H4: PRE009 | I4: PRE004 | J4: PRE005 | K4: PRE006 | L4: PRE010 | M4: PRE011 | N4: PRE012 | O4: PRE013 | P4: PRE014 | Q4: PRE015
B5: ID_Ativo | C5: ATI001 | D5: ATI001 | E5: ATI001 | F5: ATI003 | G5: ATI003 | H5: ATI003 | I5: ATI002 | J5: ATI002 | K5: ATI002 | L5: ATI004 | M5: ATI004 | N5: ATI004 | O5: ATI005 | P5: ATI005 | Q5: ATI005
B6: Data | C6: 46266 | D6: 46267 | E6: 46268 | F6: 38.5 | G6: 46267 | H6: 46268 | I6: 46266 | J6: 46267 | K6: 46268 | L6: 46266 | M6: 46267 | N6: 46268 | O6: 46266 | P6: 46267 | Q6: 46268
B7: preco_Fechamento | C7: 35.2 | D7: 35.85 | E7: 35.5 | F7: 38.5 | G7: 38.9 | H7: 39.2 | I7: 62.4 | J7: 63.1 | K7: 62.8 | L7: 14.8 | M7: 15.05 | N7: 14.95 | O7: 52 | P7: 52.7 | Q7: 52.4
B8: Volume | C8: 2500000 | D8: 2800000 | E8: 2650000 | F8: 1500000 | G8: 1650000 | H8: 3654000 | I8: 1800000 | J8: 1950000 | K8: 2100000 | L8: 2200000 | M8: 2350000 | N8: 2400000 | O8: 950000 | P8: 1050000 | Q8: 1100000
B9: Moeda | C9: BRL | D9: BRL | E9: BRL | F9: BRL | G9: BRL | H9: BRL | I9: BRL | J9: BRL | K9: BRL | L9: BRL | M9: BRL | N9: BRL | O9: BRL | P9: BRL | Q9: BRL
B10: Tipo_Dado | C10: Fictício | D10: Fictício | E10: Fictício | F10: Fictício | G10: Fictício | H10: Fictício | I10: Fictício | J10: Fictício | K10: Fictício | L10: Fictício | M10: Fictício | N10: Fictício | O10: Fictício | P10: Fictício | Q10: Fictício
B11: Fonte | C11: Simulação | D11: Simulação | E11: Simulação | F11: Simulação | G11: Simulação | H11: Simulação | I11: Simulação | J11: Simulação | K11: Simulação | L11: Simulação | M11: Simulação | N11: Simulação | O11: Simulação | P11: Simulação | Q11: Simulação
B15: ID_Preco | C15: ID_Ativo | D15: Data | E15: Preco_Fechamento | F15: Volume | G15: Moeda | H15: Tipo_Dado | I15: Fonte
B16: PRE001 | C16: ATI001 | D16: 46266 | E16: 35.2 | F16: 1500000 | G16: BRL | H16: Fictício | I16: Simulação
B17: PRE002 | C17: ATI001 | D17: 46266 | E17: 35.85 | F17: 1650000 | G17: BRL | H17: Fictício | I17: Simulação
B18: PRE003 | C18: ATI001 | D18: 46266 | E18: 35.5 | F18: 1580000 | G18: BRL | H18: Fictício | I18: Simulação
B19: PRE004 | C19: ATI002 | D19: 46266 | E19: 62.4 | F19: 1200000 | G19: BRL | H19: Fictício | I19: Simulação
B20: PRE005 | C20: ATI002 | D20: 46266 | E20: 63.1 | F20: 1350000 | G20: BRL | H20: Fictício | I20: Simulação
B21: PRE006 | C21: ATI002 | D21: 46267 | E21: 62.8 | F21: 1280000 | G21: BRL | H21: Fictício | I21: Simulação
B22: PRE007 | C22: ATI003 | D22: 46267 | E22: 38.5 | F22: 950000 | G22: BRL | H22: Fictício | I22: Simulação
B23: PRE008 | C23: ATI003 | D23: 46267 | E23: 38.9 | F23: 1100000 | G23: BRL | H23: Fictício | I23: Simulação
B24: PRE009 | C24: ATI003 | D24: 46267 | E24: 39.2 | F24: 1050000 | G24: BRL | H24: Fictício | I24: Simulação
B25: PRE010 | C25: ATI004 | D25: 46267 | E25: 14.8 | F25: 2100000 | G25: BRL | H25: Fictício | I25: Simulação
B26: PRE011 | C26: ATI004 | D26: 46268 | E26: 15.05 | F26: 2250000 | G26: BRL | H26: Fictício | I26: Simulação
B27: PRE012 | C27: ATI004 | D27: 46268 | E27: 14.95 | F27: 2180000 | G27: BRL | H27: Fictício | I27: Simulação
... B30: PRE015 | C30: ATI005 | D30: 46268 | E30: 52.4 | F30: 790000 | G30: BRL | H30: Fictício | I30: Simulação

Sheet tbMovimentos
B2: ID_Movimento | C2: Data | D2: ID_Ativo | E2: Tipo_Movimento | F2: Quantidade | G2: Preco_Unitario | H2: Taxas | I2: Valor_Total | J2: Tipo_Dado | K2: Fonte
B3: MOV001 | C3: 46269 | D3: ATI001 | E3: Compra | F3: 100 | G3: 35.5 | H3: 5 | I3: =F3*G3+H3 -> 3555 | J3: Fictício | K3: Simulação
B4: MOV002 | C4: 46270 | D4: ATI002 | E4: Compra | F4: 50 | G4: 62.8 | H4: 4 | I4: =F4*G4+H4 -> 3144 | J4: Fictício | K4: Simulação
B5: MOV003 | C5: 46271 | D5: ATI003 | E5: Compra | F5: 80 | G5: 39.2 | H5: 3.5 | I5: =F5*G5+H5 -> 3139.5 | J5: Fictício | K5: Simulação
B6: MOV004 | C6: 46272 | D6: ATI001 | E6: Venda | F6: 20 | G6: 36 | H6: 2 | I6: =F6*G6-H6 -> 718 | J6: Fictício | K6: Simulação
B7: MOV005 | C7: 46273 | D7: ATI005 | E7: Compra | F7: 30 | G7: 52.4 | H7: 3 | I7: =F7*G7+H7 -> 1575 | J7: Fictício | K7: Simulação

Sheet tbCarteiraInvestimento
B2: ID_Posicao | C2: ID_Ativo | D2: Quantidade_Comprada | E2: Quantidade_Vendida | F2: Quantidade_Atual | G2: Preco_Medio_Compra | H2: Valor_Investido | I2: Preco_Atual | J2: Valor_Mercado | K2: Lucro_Prejuizo | L2: Rentabilidade | M2: Tipo_Dado
B3: POS001 | C3: ATI001 | D3: =SUMIF(C3:C7,tbMovimentos!D3,tbMovimentos!F3:F7) -> 100 | E3: =_xlfn.SUMIFS(tbMovimentos!F3:F7,tbMovimentos!D3:D7,C3,tbMovimentos!E3:E7,"Venda") -> 20 | F3: =D3-E3 -> 80 | G3: =_xlfn.AVERAGEIFS(tbMovimentos!G3:G7,tbMovimentos!D3:D7,C3,tbMovimentos!E3:E7,"Compra") -> 35.5 | H3: =F3*G3 -> 2840 | I3: =VLOOKUP(C3,tbPrecosMercado!C16:E30,3,0) -> 35.2 | J3: =F3*I3 -> 2816 | K3: =J3-H3 -> -24 | L3: =K3/H3 -> -0.0084507042 | M3: Fictício
B4: POS002 | C4: ATI002 | D4: =SUMIF(tbMovimentos!D3:D7,C4,tbMovimentos!F3:F7) -> 50 | E4: =_xlfn.SUMIFS(tbMovimentos!F3:F7,tbMovimentos!D3:D7,C4,tbMovimentos!E3:E7,"Venda") -> 0 | F4: =D4-E4 -> 50 | G4: =_xlfn.AVERAGEIFS(tbMovimentos!G3:G7,tbMovimentos!D3:D7,C4,tbMovimentos!E3:E7,"Compra") -> 62.8 | H4: =F4*G4 -> 3140 | I4: =VLOOKUP(C4,tbPrecosMercado!C17:E31,3,0) -> 62.4 | J4: =F4*I4 -> 3120 | K4: =J4-H4 -> -20 | L4: =K4/H4 -> -0.0063694268 | M4: Fictício
B5: POS003 | C5: ATI003 | D5: =SUMIF(tbMovimentos!D3:D7,C5,tbMovimentos!F3:F7) -> 80 | E5: =_xlfn.SUMIFS(tbMovimentos!F4:F8,tbMovimentos!D4:D8,C5,tbMovimentos!E4:E8,"Venda") -> 0 | F5: =D5-E5 -> 80 | G5: =_xlfn.AVERAGEIFS(tbMovimentos!G3:G7,tbMovimentos!D3:D7,C5,tbMovimentos!E3:E7,"Compra") -> 39.2 | H5: =F5*G5 -> 3136 | I5: =VLOOKUP(C5,tbPrecosMercado!C18:E32,3,0) -> 38.5 | J5: =F5*I5 -> 3080 | K5: =J5-H5 -> -56 | L5: =K5/H5 -> -0.017857143 | M5: Fictício
B6: POS004 | C6: ATI004 | D6: =SUMIF(tbMovimentos!D3:D7,C6,tbMovimentos!F3:F7) -> 0 | E6: =_xlfn.SUMIFS(tbMovimentos!F5:F9,tbMovimentos!D5:D9,C6,tbMovimentos!E5:E9,"Venda") -> 0 | F6: =D6-E6 -> 0 | G6: =IFERROR(_xlfn.AVERAGEIFS(tbMovimentos!G3:G7,tbMovimentos!D3:D7,C6,tbMovimentos!E3:E7,"Compra"),0) -> 0 | H6: =F6*G6 -> 0 | I6: =VLOOKUP(C6,tbPrecosMercado!C19:E33,3,0) -> 14.8 | J6: =F6*I6 -> 0 | K6: =J6-H6 -> 0 | L6: =IFERROR(K6/J6,"0") -> 0 | M6: Fictício
B7: POS005 | C7: ATI005 | D7: =SUMIF(tbMovimentos!D3:D7,C7,tbMovimentos!F3:F7) -> 30 | E7: =_xlfn.SUMIFS(tbMovimentos!F3:F7,tbMovimentos!D3:D7,C7,tbMovimentos!E3:E7,"Venda") -> 0 | F7: =D7-E7 -> 30 | G7: =_xlfn.AVERAGEIFS(tbMovimentos!G5:G9,tbMovimentos!D5:D9,C7,tbMovimentos!E5:E9,"Compra") -> 52.4 | H7: =F7*G7 -> 1572 | I7: =VLOOKUP(C7,tbPrecosMercado!C20:E34,3,0) -> 52 | J7: =F7*I7 -> 1560 | K7: =J7-H7 -> -12 | L7: =K7/H7 -> -0.0076335878 | M7: Fictício

Sheet Base_DRE
B2: ID_DRE | C2: ID_Empresa | D2: Periodo | E2: Receita_Bruta | F2: Deducoes | G2: Receita_Líquida | H2: Custos | I2: Lucro_Bruto | J2: Despesas_Operacionais | K2: Resultado_Operacional | L2: Impostos | M2: Resultado_Líquido | N2: Tipo_Dado
B3: DRE001 | C3: EMP001 | D3: 46295 | E3: 5000000 | F3: 500000 | G3: =E3-F3 -> 4500000 | H3: 2500000 | I3: =G3-H3 -> 2000000 | J3: 800000 | K3: =I3-J3 -> 1200000 | L3: 300000 | M3: =K3-L3 -> 900000 | N3: Fictício
B4: DRE002 | C4: EMP002 | D4: 46295 | E4: 4200000 | F4: 420000 | G4: =E4-F4 -> 3780000 | H4: 2200000 | I4: =G4-H4 -> 1580000 | J4: 650000 | K4: =I4-J4 -> 930000 | L4: 232500 | M4: =K4-L4 -> 697500 | N4: Fictício
B5: DRE003 | C5: EMP003 | D5: 46295 | E5: 6000000 | F5: 600000 | G5: =E5-F5 -> 5400000 | H5: 2700000 | I5: =G5-H5 -> 2700000 | J5: 900000 | K5: =I5-J5 -> 1800000 | L5: 450000 | M5: =K5-L5 -> 1350000 | N5: Fictício
B6: DRE004 | C6: EMP004 | D6: 46295 | E6: 3500000 | F6: 350000 | G6: =E6-F6 -> 3150000 | H6: 1700000 | I6: =G6-H6 -> 1450000 | J6: 600000 | K6: =I6-J6 -> 850000 | L6: 212500 | M6: =K6-L6 -> 637500 | N6: Fictício
B7: DRE005 | C7: EMP005 | D7: 46295 | E7: 2800000 | F7: 280000 | G7: =E7-F7 -> 2520000 | H7: 1200000 | I7: =G7-H7 -> 1320000 | J7: 500000 | K7: =I7-J7 -> 820000 | L7: 205000 | M7: =K7-L7 -> 615000 | N7: Fictício

Sheet Base_BP
B2: ID_BP | C2: ID_Empresa | D2: Periodo | E2: Ativo_Circulante | F2: Ativo_Não_Circulante | G2: Ativo_Total | H2: Passivo_Circulante | I2: Passivo_Não_Circulante | J2: Passivo_Total | K2: Patrimonio_Liquido | L2: Passivo_PL_Total | M2: Conferencia | N2: Tipo_Dado
B3: BP001 | C3: EMP001 | D3: 46295 | E3: 1800 | F3: 4200 | G3: =SUM(E3,F3) -> 6000 | H3: 1200 | I3: 1800 | J3: =SUM(H3,I3) -> 3000 | K3: =G3-J3 -> 3000 | L3: =K3+J3 -> 6000 | M3: =IF(G3=L3,"Ok","Verificar") -> Ok | N3: Fictício
B4: BP002 | C4: EMP002 | D4: 46295 | E4: 1500 | F4: 3500 | G4: =SUM(E4,F4) -> 5000 | H4: 1000 | I4: 1500 | J4: =SUM(H4,I4) -> 2500 | K4: =G4-J4 -> 2500 | L4: =K4+J4 -> 5000 | M4: =IF(G4=L4,"Ok","Verificar") -> Ok | N4: Fictício
B5: BP003 | C5: EMP003 | D5: 46295 | E5: 2200 | F5: 4800 | G5: =SUM(E5,F5) -> 7000 | H5: 1400 | I5: 2100 | J5: =SUM(H5,I5) -> 3500 | K5: =G5-J5 -> 3500 | L5: =K5+J5 -> 7000 | M5: =IF(G5=L5,"Ok","Verificar") -> Ok | N5: Fictício
B6: BP004 | C6: EMP004 | D6: 46295 | E6: 1100 | F6: 2900 | G6: =SUM(E6,F6) -> 4000 | H6: 800 | I6: 1200 | J6: =SUM(H6,I6) -> 2000 | K6: =G6-J6 -> 2000 | L6: =K6+J6 -> 4000 | M6: =IF(G6=L6,"Ok","Verificar") -> Ok | N6: Fictício
B7: BP005 | C7: EMP005 | D7: 46295 | E7: 900 | F7: 2600 | G7: =SUM(E7,F7) -> 3500 | H7: 700 | I7: 1000 | J7: =SUM(H7,I7) -> 1700 | K7: =G7-J7 -> 1800 | L7: =K7+J7 -> 3500 | M7: =IF(G7=L7,"Ok","Verificar") -> Ok | N7: Fictício

Sheet Base_DFC
B2: ID_Fluxo | C2: ID_Empresa | D2: Periodo | E2: Entradas_Operacionais | F2: Saidas_Operacionais | G2: Fluxo_Operacional | H2: Entradas_Investimento | I2: Saidas_Investimento | J2: Fluxo_Investimento | K2: Entradas_Financiamento | L2: Saidas_Financiamento | M2: Fluxo_Financiamento | N2: Fluxo_Liquido | O2: Tipo_Dado
B3: FLX001 | C3: EMP001 | D3: 46295 | E3: 900000 | F3: 550000 | G3: =SUM(E3,-F3) -> 350000 | H3: 20000 | I3: 180000 | J3: =SUM(H3,-I3) -> -160000 | K3: 100000 | L3: 120000 | M3: =SUM(K3,-L3) -> -20000 | N3: =SUM(G3,J3,M3) -> 170000 | O3: Fictício
B4: FLX002 | C4: EMP002 | D4: 46295 | E4: 750000 | F4: 400000 | G4: =SUM(E4,-F4) -> 350000 | H4: 15000 | I4: 220000 | J4: =SUM(H4,-I4) -> -205000 | K4: 80000 | L4: 90000 | M4: =SUM(K4,-L4) -> -10000 | N4: =SUM(G4,J4,M4) -> 135000 | O4: Fictício
B5: FLX003 | C5: EMP003 | D5: 46295 | E5: 1000000 | F5: 650000 | G5: =SUM(E5,-F5) -> 350000 | H5: 30000 | I5: 250000 | J5: =SUM(H5,-I5) -> -220000 | K5: 150000 | L5: 100000 | M5: =SUM(K5,-L5) -> 50000 | N5: =SUM(G5,J5,M5) -> 180000 | O5: Fictício
B6: FLX004 | C6: EMP004 | D6: 46295 | E6: 500000 | F6: 300000 | G6: =SUM(E6,-F6) -> 200000 | H6: 10000 | I6: 90000 | J6: =SUM(H6,-I6) -> -80000 | K6: 50000 | L6: 40000 | M6: =SUM(K6,-L6) -> 10000 | N6: =SUM(G6,J6,M6) -> 130000 | O6: Fictício
B7: FLX005 | C7: EMP005 | D7: 46295 | E7: 420000 | F7: 250000 | G7: =SUM(E7,-F7) -> 170000 | H7: 12000 | I7: 110000 | J7: =SUM(H7,-I7) -> -98000 | K7: 30000 | L7: 50000 | M7: =SUM(K7,-L7) -> -20000 | N7: =SUM(G7,J7,M7) -> 52000 | O7: Fictício

Sheet Indicadores
B2: Indicador | C2: Resultado
B3: Receita_Liquida_Total | C3: =SUM(Base_DRE!G3:G7) -> 19350000
B4: Lucro_Liquido_Total | C4: =SUM(Base_DRE!M3:M7) -> 4200000
B5: Fluxo_De_Caixa_Liquido_Total | C5: =SUM(Base_DFC!N3:N7) -> 667000
B6: Ativos_Totais | C6: =SUM(Base_BP!G3:G7) -> 25500
B7: Passivos_Totais | C7: =SUM(Base_BP!J3:J7) -> 12700
B8: Patrimoio_Liquido_Total | C8: =SUM(Base_BP!K3:K7) -> 12800
B9: Empresas_Analisadas | C9: =COUNTA(Base_DRE!C3:C7) -> 5
B11: Indicadores_De_Desempenho | C11: Resultado
B12: Margem_Liquida_Consolidada | C12: =IFERROR(C4/C3,0) -> 0.21705426
B13: Margem_Operacional_Consolidada | C13: =IFERROR(SUM(Base_DRE!K3:K7)/C3,0) -> 0.28940568
B14: Rentabilidade_Da_Carteira | C14: =IFERROR(SUM(tbCarteiraInvestimento!K3:K7)/SUM(tbCarteiraInvestimento!H3:H7),0) -> -0.010479042
B15: Ativos_Sobre_Passivos | C15: =IFERROR(C6/C7,0) -> 2.007874
B16: Empresas_Com_Lucro_Positivo | C16: =COUNTIF(Base_DRE!M3:M7,">0") -> 5
B17: Empresas_Com_Fluxo_De_Caixa_Positivo | C17: =COUNTIF(Base_DFC!N3:N7,">0") -> 5

Sheet Dashboard
D3: CORPORATE FINANCE & INVESTMENT INTELLIGENCE
D4: Análise financeira e de investimentos | Dados fictícios | Setembro de 2026
D5: RECEITA LÍQUIDA TOTAL | E5: LUCRO LÍQUIDO TOTAL
D6: =Indicadores!C3 -> 19350000 | E6: =Indicadores!C4 -> 4200000
D8: FLUXO DE CAIXA LÍQUIDO | E8: EMPRESAS ANALISADAS
D9: =Indicadores!C5 -> 667000 | E9: =Indicadores!C9 -> 5
D11: MARGEM OPERACIONAL | E11: RENTABILIDADE DA CARTEIRA
D12: =Indicadores!C13 -> 0.28940568 | E12: =Indicadores!C14 -> -0.010479042
D15: Empresa | E15: Lucro Líquido
D16: Petrobras (PETR4) | E16: =Base_DRE!M3 -> 900000
D17: Vale (VALE3) | E17: =Base_DRE!M4 -> 697500
D18: Itaú (ITUB4) | E18: =Base_DRE!M5 -> 1350000
D19: Ambev (ABEV3) | E19: =Base_DRE!M6 -> 637500
D20: WEG (WEGE3) | E20: =Base_DRE!M7 -> 615000
